fastapi_satella_metrics/__init__.py
fastapi_satella_metrics/prometheus_exporter.py
fastapi_satella_metrics-2.0.0.dist-info/LICENSE.md
fastapi_satella_metrics-2.0.0.dist-info/METADATA
fastapi_satella_metrics-2.0.0.dist-info/WHEEL
fastapi_satella_metrics-2.0.0.dist-info/top_level.txt
fastapi_satella_metrics-2.0.0.dist-info/RECORD
