Metadata-Version: 2.1
Name: fastapi-satella-metrics
Version: 2.0.0
Summary: A library for attaching Satella metrics to FastAPI
Home-page: https://github.com/Dronehub/fastapi-satella-metrics
Author: Norbert Ozga
Author-email: norbert.ozga@dronehub.ai
License: UNKNOWN
Project-URL: Code, https://github.com/Dronehub/fastapi-satella-metrics
Project-URL: Issue tracker, https://github.com/Dronehub/fastapi-satella-metrics/issues
Platform: UNKNOWN
Classifier: Development Status :: 4 - Beta
Classifier: Programming Language :: Python
Classifier: Programming Language :: Python :: 3.5
Classifier: Programming Language :: Python :: 3.6
Classifier: Programming Language :: Python :: 3.7
Classifier: Programming Language :: Python :: 3.8
Classifier: Programming Language :: Python :: 3.9
Classifier: Programming Language :: Python :: Implementation :: CPython
Classifier: Programming Language :: Python :: Implementation :: PyPy
Classifier: Operating System :: OS Independent
Classifier: License :: OSI Approved :: MIT License
Classifier: Topic :: Software Development :: Libraries
Requires-Python: !=2.7.*,!=3.0.*,!=3.1.*,!=3.2.*,!=3.3.*,!=3.4.*,!=3.5.*,!=3.6.*
Requires-Dist: satella
Requires-Dist: fastapi
Requires-Dist: starlette
